rusticsoup-0.5.0.dist-info/METADATA
rusticsoup-0.5.0.dist-info/WHEEL
rusticsoup-0.5.0.dist-info/licenses/LICENSE
rusticsoup/__init__.py
rusticsoup/__init__.pyi
rusticsoup/extractors.py
rusticsoup/json_utils.py
rusticsoup/rusticsoup.abi3.so
rusticsoup/rusticsoup.pyi
rusticsoup-0.5.0.dist-info/RECORD
