Metadata-Version: 2.4
Name: rusticsoup
Version: 0.5.0
Classifier: Development Status :: 4 - Beta
Classifier: Intended Audience :: Developers
Classifier: License :: OSI Approved :: MIT License
Classifier: Programming Language :: Python :: 3
Classifier: Programming Language :: Python :: 3 :: Only
Classifier: Programming Language :: Python :: 3.9
Classifier: Programming Language :: Python :: 3.10
Classifier: Programming Language :: Python :: 3.11
Classifier: Programming Language :: Python :: 3.12
Classifier: Programming Language :: Python :: 3.13
Classifier: Programming Language :: Python :: 3.14
Classifier: Programming Language :: Python :: Implementation :: CPython
Classifier: Programming Language :: Rust
Classifier: Topic :: Internet :: WWW/HTTP
Classifier: Topic :: Software Development :: Libraries :: Python Modules
Classifier: Topic :: Text Processing :: Markup :: HTML
Requires-Dist: pytest>=8 ; extra == 'dev'
Requires-Dist: hypothesis>=6 ; extra == 'dev'
Requires-Dist: ruff>=0.5 ; extra == 'dev'
Requires-Dist: black>=24 ; extra == 'dev'
Requires-Dist: mypy>=1 ; extra == 'dev'
Requires-Dist: pytest-benchmark>=4 ; extra == 'dev'
Requires-Dist: pre-commit>=3 ; extra == 'dev'
Provides-Extra: dev
License-File: LICENSE
Summary: Lightning-fast HTML parser and data extractor with WebPage API - BeautifulSoup alternative built in Rust
Keywords: html,parser,scraping,web,extraction,beautifulsoup,rust,webpage,web-poet
Author: Iristech Systems
License: MIT
Requires-Python: >=3.9
Project-URL: Homepage, https://github.com/iristech-systems/RusticSoup
Project-URL: Repository, https://github.com/iristech-systems/RusticSoup
Project-URL: Documentation, https://github.com/iristech-systems/RusticSoup#readme
Project-URL: Issues, https://github.com/iristech-systems/RusticSoup/issues
